oshino_jmx/__init__.py
oshino_jmx/agent.py
oshino_jmx/version.py
oshino_jmx-0.1.1.dist-info/DESCRIPTION.rst
oshino_jmx-0.1.1.dist-info/METADATA
oshino_jmx-0.1.1.dist-info/RECORD
oshino_jmx-0.1.1.dist-info/WHEEL
oshino_jmx-0.1.1.dist-info/metadata.json
oshino_jmx-0.1.1.dist-info/top_level.txt
