Metadata-Version: 2.0
Name: oshino-jmx
Version: 0.1.1
Summary: Collect JMX metrics from JVM services
Home-page: UNKNOWN
Author: Šarūnas Navickas
Author-email: zaibacu@gmail.com
License: UNKNOWN
Platform: UNKNOWN
Requires-Dist: oshino
Requires-Dist: oshino-statsd
